{
  "hand_authored": false,
  "key": "https://developer.nlr.gov/api/pvwatts/v8.json?array_type=1&azimuth=180.0&dataset=nsrdb&dc_ac_ratio=1.2&lat=39.74&lon=-105.18&losses=14.0&module_type=0&system_capacity=4.0&tilt=25.0&timeframe=monthly",
  "response": {
    "headers": {
      "x-ratelimit-limit": "1000",
      "x-ratelimit-remaining": "995"
    },
    "json": {
      "errors": [],
      "inputs": {
        "array_type": "1",
        "azimuth": "180.0",
        "dataset": "nsrdb",
        "dc_ac_ratio": "1.2",
        "lat": "39.74",
        "lon": "-105.18",
        "losses": "14.0",
        "module_type": "0",
        "system_capacity": "4.0",
        "tilt": "25.0",
        "timeframe": "monthly"
      },
      "outputs": {
        "ac_annual": 6082.463603758244,
        "ac_monthly": [
          423.6915848521475,
          452.8023624104732,
          566.255204306788,
          565.0381926616203,
          551.5978075383127,
          563.3570386921626,
          571.4025346921547,
          542.4792330544021,
          530.3720773044756,
          494.0218335573743,
          421.2077776224135,
          400.2379570659272
        ],
        "capacity_factor": 17.35862900615939,
        "dc_monthly": [
          444.0507676158347,
          476.2286195656063,
          595.0016909518274,
          594.7779329629028,
          579.3975994517895,
          590.9531114695666,
          599.6002103582655,
          569.2392735466683,
          555.7557267855586,
          517.6547839168356,
          441.5742265822643,
          419.4373267420011
        ],
        "poa_monthly": [
          125.739806808037,
          138.0864463542232,
          177.5386211859448,
          179.1389236258759,
          181.7240246353656,
          192.3987700800625,
          197.9321538311852,
          185.2003730175161,
          178.0685825300899,
          158.1345162795622,
          130.3131957627608,
          118.5587298375077
        ],
        "solrad_annual": 5.377131996621468,
        "solrad_monthly": [
          4.056122800259259,
          4.931658798365113,
          5.727052296320801,
          5.971297454195865,
          5.862065310818245,
          6.413292336002085,
          6.384908188102749,
          5.974205581210195,
          5.935619417669662,
          5.101113428372973,
          4.343773192092028,
          3.824475156048637
        ]
      },
      "ssc_info": {
        "build": "Linux 64 bit GNU/C++ Oct 18 2023 07:13:03",
        "module": "pvwattsv8",
        "version": 280
      },
      "station_info": {
        "city": "",
        "country": "United States",
        "distance": 1120,
        "elev": 1819.599975585938,
        "lat": 39.72999954223633,
        "location": "145809",
        "lon": -105.1800003051758,
        "solar_resource_file": "145809.csv",
        "state": "Colorado",
        "tz": -7.0,
        "weather_data_source": "NSRDB PSM V3 GOES tmy-2020 3.2.0"
      },
      "version": "8.5.0",
      "warnings": []
    },
    "status": 200
  }
}
